[
    {
        "model": "auth.group",
        "pk": 1,
        "fields": {
            "name": "default",
            "permissions": [
                81,
                82,
                83,
                84,
                97,
                98,
                99,
                100
            ]
        }
    },
    {
        "model": "auth.group",
        "pk": 2,
        "fields": {
            "name": "mod",
            "permissions": [
                37,
                38,
                39,
                40
            ]
        }
    }
]